README.md
setup.py
cv2box/__init__.py
cv2box.egg-info/PKG-INFO
cv2box.egg-info/SOURCES.txt
cv2box.egg-info/dependency_links.txt
cv2box.egg-info/requires.txt
cv2box.egg-info/top_level.txt
cv2box/cv_gears/__init__.py
cv2box/cv_gears/concurrent_wrapper.py
cv2box/cv_gears/cv_audio_thread.py
cv2box/cv_gears/cv_multi_video_thread.py
cv2box/cv_gears/cv_threads_base.py
cv2box/cv_gears/cv_video_thread.py
cv2box/cv_gears/keyboard_listener_thread.py
cv2box/cv_gears/vidgear/__init__.py
cv2box/cv_gears/vidgear/camgear.py
cv2box/cv_gears/vidgear/helper.py
cv2box/cv_ops/__init__.py
cv2box/cv_ops/cv_audio.py
cv2box/cv_ops/cv_bbox.py
cv2box/cv_ops/cv_camera.py
cv2box/cv_ops/cv_excel.py
cv2box/cv_ops/cv_file.py
cv2box/cv_ops/cv_folder.py
cv2box/cv_ops/cv_image.py
cv2box/cv_ops/cv_queue.py
cv2box/cv_ops/cv_rotate.py
cv2box/cv_ops/cv_srt.py
cv2box/cv_ops/cv_video.py
cv2box/utils/__init__.py
cv2box/utils/math.py
cv2box/utils/scheduler.py
cv2box/utils/send_notify.py
cv2box/utils/util.py
cv2box/utils/encrypt/__init__.py
cv2box/utils/encrypt/cv_encrypt.py
cv2box/utils/logging/__init__.py
cv2box/utils/logging/cv_logging.py