Metadata-Version: 2.4
Name: cv2box
Version: 0.6.0
Summary: cv toolbox
Home-page: https://github.com/ykk648/cv2box
Author: ykk648
Author-email: ykk648@gmail.com
Project-URL: Bug Tracker, https://github.com/ykk648/cv2box/issues
Classifier: Programming Language :: Python :: 3
Classifier: License :: OSI Approved :: GNU General Public License v3 (GPLv3)
Classifier: Operating System :: OS Independent
Requires-Python: >=3.10
Requires-Dist: numpy
Requires-Dist: tqdm
Requires-Dist: opencv-python
Provides-Extra: light
Provides-Extra: full
Requires-Dist: apscheduler; extra == "full"
Requires-Dist: numexpr; extra == "full"
Requires-Dist: h5py; extra == "full"
Requires-Dist: yaml; extra == "full"
Dynamic: author
Dynamic: author-email
Dynamic: classifier
Dynamic: description
Dynamic: description-content-type
Dynamic: home-page
Dynamic: project-url
Dynamic: provides-extra
Dynamic: requires-dist
Dynamic: requires-python
Dynamic: summary
